connectionmaster/__init__.py
connectionmaster/__main__.py
connectionmaster-0.0.8.dist-info/LICENSE
connectionmaster-0.0.8.dist-info/METADATA
connectionmaster-0.0.8.dist-info/WHEEL
connectionmaster-0.0.8.dist-info/top_level.txt
connectionmaster-0.0.8.dist-info/RECORD
