Metadata-Version: 2.1
Name: connectionmaster
Version: 0.0.8
Summary: A python utility for remote server management
Home-page: https://github.com/nathansmerrill/connectionmaster
Author: Nathan Merrill
Author-email: mathiscool3000@gmail.com
License: UNKNOWN
Platform: UNKNOWN
Classifier: Programming Language :: Python :: 3
Classifier: Operating System :: OS Independent
Requires-Python: >=3.6
Requires-Dist: pyyaml
Requires-Dist: blinkparse
